COPYING.txt
MANIFEST.in
README.md
setup.py
xpyth/__init__.py
xpyth.egg-info/PKG-INFO
xpyth.egg-info/SOURCES.txt
xpyth.egg-info/dependency_links.txt
xpyth.egg-info/requires.txt
xpyth.egg-info/top_level.txt