Metadata-Version: 1.1
Name: xpyth
Version: 0.2.0
Summary: Generate XPath expressions from Python comprehensions
Home-page: https://github.com/hchasestevens/xpyth
Author: H. Chase Stevens
Author-email: chase@chasestevens.com
License: MIT
Keywords: xpath xml html
Platform: UNKNOWN
Classifier: Development Status :: 2 - Pre-Alpha
Classifier: Programming Language :: Python
Classifier: Programming Language :: Python :: 2
Classifier: Programming Language :: Python :: 2.7
Classifier: Programming Language :: Python :: 3
Classifier: Programming Language :: Python :: 3.6
Classifier: Intended Audience :: Developers
Classifier: Operating System :: OS Independent
Classifier: License :: OSI Approved :: MIT License
Classifier: Natural Language :: English
Classifier: Topic :: Internet :: WWW/HTTP
Classifier: Topic :: Software Development :: Code Generators
